{"cameraMode":{"drawMode":0,"name":"Shaded","section":"Shading Mode"},"sceneLighting":true,"audioPlay":false,"sceneViewState":{"showFog":true,"showMaterialUpdate":false,"showSkybox":true,"showFlares":true,"showImageEffects":true,"showParticleSystems":true,"showVisualEffectGraphs":true,"m_FxEnabled":true},"in2DMode":false,"pivot":{"x":8.50422477722168,"y":-3.996798038482666,"z":3.802629232406616},"rotation":{"x":-0.17052343487739564,"y":-0.6967371702194214,"z":0.1763140857219696,"w":-0.6741183400154114},"size":11.228096961975098,"orthographic":false}